saenopy/__init__.py
saenopy/build_beams.py
saenopy/conjugate_gradient.py
saenopy/examples.py
saenopy/export_html.py
saenopy/get_deformations.py
saenopy/gui/__init__.py
saenopy/gui/code/__init__.py
saenopy/gui/code/code_editor.py
saenopy/gui/code/gui_code.py
saenopy/gui/code/script_file.py
saenopy/gui/code/syntax.py
saenopy/gui/code_evluate_normal.py
saenopy/gui/common/AddFilesDialog.py
saenopy/gui/common/BatchEvaluateBase.py
saenopy/gui/common/ModuleColorBar.py
saenopy/gui/common/ModuleScaleBar.py
saenopy/gui/common/PipelineModule.py
saenopy/gui/common/PlottingWindowBase.py
saenopy/gui/common/QExtendedGraphicsView.py
saenopy/gui/common/QTimeSlider.py
saenopy/gui/common/QtShortCuts.py
saenopy/gui/common/__init__.py
saenopy/gui/common/code_export.py
saenopy/gui/common/gui_classes.py
saenopy/gui/common/lif_reader.py
saenopy/gui/common/patch_lifreader.py
saenopy/gui/common/resources.py
saenopy/gui/common/sigmoid_widget.py
saenopy/gui/common/stack_preview.py
saenopy/gui/common/stack_selector.py
saenopy/gui/common/stack_selector_crop.py
saenopy/gui/common/stack_selector_leica.py
saenopy/gui/common/stack_selector_tif.py
saenopy/gui/gui_master.py
saenopy/gui/material_fit/gui_fit.py
saenopy/gui/orientation/__init__.py
saenopy/gui/orientation/gui_orientation.py
saenopy/gui/orientation/modules/AddFilesDialog.py
saenopy/gui/solver/__init__.py
saenopy/gui/solver/analyze/PlottingWindow.py
saenopy/gui/solver/analyze/__init__.py
saenopy/gui/solver/gui_solver.py
saenopy/gui/solver/modules/BatchEvaluate.py
saenopy/gui/solver/modules/DeformationDetector.py
saenopy/gui/solver/modules/FittedMesh.py
saenopy/gui/solver/modules/MeshCreator.py
saenopy/gui/solver/modules/Regularizer.py
saenopy/gui/solver/modules/ResultView.py
saenopy/gui/solver/modules/StackDisplay.py
saenopy/gui/solver/modules/VTK_Toolbar.py
saenopy/gui/solver/modules/__init__.py
saenopy/gui/solver/modules/exporter/ExportRenderCommon.py
saenopy/gui/solver/modules/exporter/Exporter.py
saenopy-1.0.6.dist-info/LICENSE.txt
saenopy-1.0.6.dist-info/METADATA
saenopy-1.0.6.dist-info/WHEEL
saenopy-1.0.6.dist-info/entry_points.txt
saenopy-1.0.6.dist-info/RECORD
