Metadata-Version: 2.1
Name: saenopy
Version: 1.0.6
Summary: Semi-elastic fiber optimisation in python.
License: MIT
Author: rgerum
Author-email: 14153051+rgerum@users.noreply.github.com
Requires-Python: >=3.9,<3.13
Classifier: License :: OSI Approved :: MIT License
Classifier: Programming Language :: Python :: 3
Classifier: Programming Language :: Python :: 3.9
Classifier: Programming Language :: Python :: 3.10
Classifier: Programming Language :: Python :: 3.11
Classifier: Programming Language :: Python :: 3.12
Provides-Extra: docs
Requires-Dist: appdirs (>=1.4.4,<2.0.0)
Requires-Dist: black (>=24.4.0,<25.0.0)
Requires-Dist: h5py (>=3.8.0,<4.0.0)
Requires-Dist: imagecodecs (>=2024.9.22,<2025.0.0)
Requires-Dist: jointforces (>=1.0.7,<2.0.0)
Requires-Dist: natsort (>=8.2.0,<9.0.0)
Requires-Dist: nbsphinx (>=0.9.2,<0.10.0) ; extra == "docs"
Requires-Dist: numba (>=0.60.0,<0.61.0)
Requires-Dist: numpy (>=1.26.4)
Requires-Dist: openpiv (>=0.24.2,<0.25.0)
Requires-Dist: pyqt5 (==5.15.11)
Requires-Dist: pyvista (>=0.44.1,<0.45.0)
Requires-Dist: pyvistaqt (>=0.11.1,<0.12.0)
Requires-Dist: qimage2ndarray (>=1.9.0,<2.0.0)
Requires-Dist: qtawesome (>=1.2.1,<2.0.0)
Requires-Dist: qtrangeslider (>=0.1.5,<0.2.0)
Requires-Dist: scipy (>=1.9.3)
Requires-Dist: solidspy
Requires-Dist: sphinx (>=1.6,<7) ; extra == "docs"
Requires-Dist: sphinx-gallery (>=0.13.0,<0.14.0) ; extra == "docs"
Requires-Dist: sphinx-rtd-theme (>=1.2.2,<2.0.0) ; extra == "docs"
Requires-Dist: tqdm (>=4.64.1,<5.0.0)
